pyodrivecan/__init__.py
pyodrivecan/odrivedatabase.py
pyodrivecan/pyodrivecan.py
pyodrivecan-0.1.3.dist-info/LICENSE
pyodrivecan-0.1.3.dist-info/METADATA
pyodrivecan-0.1.3.dist-info/WHEEL
pyodrivecan-0.1.3.dist-info/top_level.txt
pyodrivecan-0.1.3.dist-info/RECORD
